link/__init__.py
link/etcd/__init__.py
link/etcd/driver.py
link/etcd/middleware.py
link.etcd-0.4.dist-info/DESCRIPTION.rst
link.etcd-0.4.dist-info/METADATA
link.etcd-0.4.dist-info/RECORD
link.etcd-0.4.dist-info/WHEEL
link.etcd-0.4.dist-info/metadata.json
link.etcd-0.4.dist-info/top_level.txt
