Metadata-Version: 2.0
Name: link.etcd
Version: 0.4
Summary: Link Etcd middleware and configuration driver
Home-page: https://github.com/linkdd/link.etcd
Author: David Delassus
Author-email: david.jose.delassus@gmail.com
License: MIT
Keywords: link etcd
Platform: UNKNOWN
Requires-Dist: b3j0f.conf (>=0.3.19)
Requires-Dist: link.middleware (>=1.5)
Requires-Dist: python-etcd (>=0.4.3)
